{
  "task": "xml_upload_to_aws", 
  "depends_on": [
    "completed@prepare_metadata_xml"
  ], 
  "tool": "upload_to_aws", 
  "command": "upload_to_aws.py", 
  "input": {
    "file_name": "bundle.EGAR00001195020.xml", 
    "object_id": "80f70a41-fe20-51da-8b57-c4eaa1f99aee", 
    "file_md5sum": "a6bfdc06ac23417c097bb4a4aec7ecfb", 
    "file": "/home/ubuntu/jtracker/worker.1499371713.aabd4754.host.2b33d591.10.10.0.20/job.EGAR00001195020.LINC-JP.CCC68T.EGAN00001196932/task.prepare_metadata_xml/bundle.EGAR00001195020.xml", 
    "file_size": 3503, 
    "bundle_id": "EGAR00001195020", 
    "project_code": "LINC-JP"
  }, 
  "runtime": {
    "docker": null
  }
}