{
  "task": "xml_upload_to_aws", 
  "depends_on": [
    "completed@prepare_metadata_xml"
  ], 
  "tool": "upload_to_aws", 
  "command": "upload_to_aws.py", 
  "input": {
    "file_name": "bundle.EGAR00001109918.xml", 
    "object_id": "bfe3729c-63e2-5ec4-b706-cf0ef191e3b6", 
    "file_md5sum": "09c44c23fcfded7bc6b90770f139f9b9", 
    "file": "/home/ubuntu/jtracker/worker.1499368884.8d58d2e6.host.2b33d591.10.10.0.20/job.EGAR00001109918.LINC-JP.HCC4T.EGAN00001085964/task.prepare_metadata_xml/bundle.EGAR00001109918.xml", 
    "file_size": 3663, 
    "bundle_id": "EGAR00001109918", 
    "project_code": "LINC-JP"
  }, 
  "runtime": {
    "docker": null
  }
}