{
  "task": "xml_upload_to_aws", 
  "depends_on": [
    "completed@prepare_metadata_xml"
  ], 
  "tool": "upload_to_aws", 
  "command": "upload_to_aws.py", 
  "input": {
    "file_name": "bundle.EGAR00001260551.xml", 
    "object_id": "75f2a03f-c910-5d56-826d-64643d04ac27", 
    "file_md5sum": "7fa048df5343543b20b5364eeca3d691", 
    "file": "/home/ubuntu/jtracker/worker.1500669053.c36d31ad.host.032f1807.10.10.0.3/job.EGAR00001260551.BTCA-JP.BD145T.EGAN00001246945/task.prepare_metadata_xml/bundle.EGAR00001260551.xml", 
    "file_size": 3184, 
    "bundle_id": "EGAR00001260551", 
    "project_code": "BTCA-JP"
  }, 
  "runtime": {
    "docker": null
  }
}