{
  "task": "xml_upload_to_aws", 
  "depends_on": [
    "completed@prepare_metadata_xml"
  ], 
  "tool": "upload_to_aws", 
  "command": "upload_to_aws.py", 
  "input": {
    "file_name": "bundle.EGAR00001110338.xml", 
    "object_id": "61cab059-63fa-5656-8505-71fc228801fc", 
    "file_md5sum": "8990892793ef02f1b908b9d3c891ebdc", 
    "file": "/home/ubuntu/jtracker/worker.1499371713.aabd4754.host.2b33d591.10.10.0.20/job.EGAR00001110338.LINC-JP.HCC12T.EGAN00001085969/task.prepare_metadata_xml/bundle.EGAR00001110338.xml", 
    "file_size": 3663, 
    "bundle_id": "EGAR00001110338", 
    "project_code": "LINC-JP"
  }, 
  "runtime": {
    "docker": null
  }
}