{
  "task": "xml_file_upload", 
  "depends_on": [
    "completed@xml_upload_to_aws", 
    "completed@prepare_metadata_xml"
  ], 
  "tool": "upload", 
  "command": "upload.py", 
  "output": [
    {
      "_jt_": {
        "worker_id": "worker.1500669053.c36d31ad.host.032f1807.10.10.0.3", 
        "workflow_version": "0.6.7", 
        "jt_version": "0.1.0rc9", 
        "task_state": "completed"
      }, 
      "runtime": {
        "task_start": 1501676636, 
        "task_stop": 1501676653
      }
    }
  ], 
  "input": {
    "file_name": "bundle.EGAR00001258893.xml", 
    "object_id": "bbf7867d-1b74-51a3-a546-b78c067467f2", 
    "file_md5sum": "ad50e6050d08e228a079858d3589d07d", 
    "file": "/home/ubuntu/jtracker/worker.1500669053.c36d31ad.host.032f1807.10.10.0.3/job.EGAR00001258893.BTCA-JP.BD99T.EGAN00001246901/task.prepare_metadata_xml/bundle.EGAR00001258893.xml", 
    "file_size": 3176, 
    "bundle_id": "EGAR00001258893"
  }, 
  "runtime": {
    "docker": null
  }
}