{
  "task": "xml_upload_to_aws", 
  "depends_on": [
    "completed@prepare_metadata_xml"
  ], 
  "tool": "upload_to_aws", 
  "command": "upload_to_aws.py", 
  "output": [
    {
      "idx_file_size": 0, 
      "idx_file_md5sum": null, 
      "_jt_": {
        "worker_id": "worker.1499371713.aabd4754.host.2b33d591.10.10.0.20", 
        "workflow_version": "0.6.7", 
        "jt_version": "0.1.0rc9", 
        "task_state": "completed"
      }, 
      "idx_file": null, 
      "allowed_upload": true, 
      "file_md5sum": "60077f5e7543e6cb8d97a4a9f5d9f26f", 
      "file": "/home/ubuntu/jtracker/worker.1499371713.aabd4754.host.2b33d591.10.10.0.20/job.EGAR00001109057.LINC-JP.BN41T.EGAN00001085954/task.prepare_metadata_xml/bundle.EGAR00001109057.xml", 
      "file_size": 3659, 
      "runtime": {
        "task_start": 1499478473, 
        "task_stop": 1499478479
      }
    }
  ], 
  "input": {
    "file_name": "bundle.EGAR00001109057.xml", 
    "object_id": "2a426fdf-cb7b-5b24-89ef-4c207bc6c32e", 
    "file_md5sum": "60077f5e7543e6cb8d97a4a9f5d9f26f", 
    "file": "/home/ubuntu/jtracker/worker.1499371713.aabd4754.host.2b33d591.10.10.0.20/job.EGAR00001109057.LINC-JP.BN41T.EGAN00001085954/task.prepare_metadata_xml/bundle.EGAR00001109057.xml", 
    "file_size": 3659, 
    "bundle_id": "EGAR00001109057", 
    "project_code": "LINC-JP"
  }, 
  "runtime": {
    "docker": null
  }
}