{
  "task": "xml_upload_to_aws", 
  "depends_on": [
    "completed@prepare_metadata_xml"
  ], 
  "tool": "upload_to_aws", 
  "command": "upload_to_aws.py", 
  "input": {
    "file_name": "bundle.EGAR00001109801.xml", 
    "object_id": "79a1b726-425f-51f2-90d6-b24b536a389d", 
    "file_md5sum": "73ae2dfe2f3bad2bc5f4b5cbdb8ed124", 
    "file": "/home/ubuntu/jtracker/worker.1499368884.8d58d2e6.host.2b33d591.10.10.0.20/job.EGAR00001109801.LINC-JP.HCC3T.EGAN00001085963/task.prepare_metadata_xml/bundle.EGAR00001109801.xml", 
    "file_size": 3659, 
    "bundle_id": "EGAR00001109801", 
    "project_code": "LINC-JP"
  }, 
  "runtime": {
    "docker": null
  }
}