{
  "task": "xml_file_upload", 
  "depends_on": [
    "completed@xml_upload_to_aws", 
    "completed@prepare_metadata_xml"
  ], 
  "tool": "upload", 
  "command": "upload.py", 
  "output": [
    {
      "_jt_": {
        "worker_id": "worker.1499368884.8d58d2e6.host.2b33d591.10.10.0.20", 
        "workflow_version": "0.6.7", 
        "jt_version": "0.1.0rc9", 
        "task_state": "completed"
      }, 
      "runtime": {
        "task_start": 1499908155, 
        "task_stop": 1499908171
      }
    }
  ], 
  "input": {
    "file_name": "bundle.EGAR00001118598.xml", 
    "object_id": "0b0f419e-3fa3-56c1-9306-0f6a19979a75", 
    "file_md5sum": "c2918ad1e9f3f756e10c0d7ccea6384d", 
    "file": "/home/ubuntu/jtracker/worker.1499368884.8d58d2e6.host.2b33d591.10.10.0.20/job.EGAR00001118598.LINC-JP.HCC118T.EGAN00001086058/task.prepare_metadata_xml/bundle.EGAR00001118598.xml", 
    "file_size": 3665, 
    "bundle_id": "EGAR00001118598"
  }, 
  "runtime": {
    "docker": null
  }
}