{
  "task": "xml_file_upload", 
  "depends_on": [
    "completed@xml_upload_to_aws", 
    "completed@prepare_metadata_xml"
  ], 
  "tool": "upload", 
  "command": "upload.py", 
  "input": {
    "file_name": "bundle.EGAR00001264060.xml", 
    "object_id": "16801765-2d8c-51a5-ac0a-0a7525da021d", 
    "file_md5sum": "21a47ca848e36cd2b46267d4f03e679f", 
    "file": "/home/ubuntu/jtracker/worker.1499368884.8d58d2e6.host.2b33d591.10.10.0.20/job.EGAR00001264060.BTCA-JP.BD228T.EGAN00001247021/task.prepare_metadata_xml/bundle.EGAR00001264060.xml", 
    "file_size": 3184, 
    "bundle_id": "EGAR00001264060"
  }, 
  "runtime": {
    "docker": null
  }
}