{
  "task": "xml_upload_to_aws", 
  "depends_on": [
    "completed@prepare_metadata_xml"
  ], 
  "tool": "upload_to_aws", 
  "command": "upload_to_aws.py", 
  "output": [
    {
      "idx_file_size": 0, 
      "idx_file_md5sum": null, 
      "_jt_": {
        "worker_id": "worker.1499371713.aabd4754.host.2b33d591.10.10.0.20", 
        "workflow_version": "0.6.7", 
        "jt_version": "0.1.0rc9", 
        "task_state": "completed"
      }, 
      "idx_file": null, 
      "allowed_upload": true, 
      "file_md5sum": "c50ee0826f1d4252bd21401abf94873b", 
      "file": "/home/ubuntu/jtracker/worker.1499371713.aabd4754.host.2b33d591.10.10.0.20/job.EGAR00001195400.LINC-JP.HCC103T.EGAN00001196884/task.prepare_metadata_xml/bundle.EGAR00001195400.xml", 
      "file_size": 3511, 
      "runtime": {
        "task_start": 1499807170, 
        "task_stop": 1499807175
      }
    }
  ], 
  "input": {
    "file_name": "bundle.EGAR00001195400.xml", 
    "object_id": "1d1ad4d1-2f90-5230-bd82-b547ed3c1717", 
    "file_md5sum": "c50ee0826f1d4252bd21401abf94873b", 
    "file": "/home/ubuntu/jtracker/worker.1499371713.aabd4754.host.2b33d591.10.10.0.20/job.EGAR00001195400.LINC-JP.HCC103T.EGAN00001196884/task.prepare_metadata_xml/bundle.EGAR00001195400.xml", 
    "file_size": 3511, 
    "bundle_id": "EGAR00001195400", 
    "project_code": "LINC-JP"
  }, 
  "runtime": {
    "docker": null
  }
}