{
  "task": "xml_file_upload", 
  "depends_on": [
    "completed@xml_upload_to_aws", 
    "completed@prepare_metadata_xml"
  ], 
  "tool": "upload", 
  "command": "upload.py", 
  "output": [
    {
      "_jt_": {
        "worker_id": "worker.1502296901.709b0ea8.host.231181a3.10.10.1.7", 
        "workflow_version": "0.6.7", 
        "jt_version": "0.1.0rc9", 
        "task_state": "completed"
      }, 
      "runtime": {
        "task_start": 1502464325, 
        "task_stop": 1502464341
      }
    }
  ], 
  "input": {
    "file_name": "bundle.EGAR00001259295.xml", 
    "object_id": "973f0c10-edd8-5be7-b0e2-cf3992c93cfb", 
    "file_md5sum": "0e490a4fe7d27880e033b958619599c6", 
    "file": "/home/ubuntu/jtracker/worker.1502296901.709b0ea8.host.231181a3.10.10.1.7/job.EGAR00001259295.BTCA-JP.BD110T.EGAN00001246911/task.prepare_metadata_xml/bundle.EGAR00001259295.xml", 
    "file_size": 3184, 
    "bundle_id": "EGAR00001259295"
  }, 
  "runtime": {
    "docker": null
  }
}