{
  "task": "xml_upload_to_aws", 
  "depends_on": [
    "completed@prepare_metadata_xml"
  ], 
  "tool": "upload_to_aws", 
  "command": "upload_to_aws.py", 
  "output": [
    {
      "idx_file_size": 0, 
      "idx_file_md5sum": null, 
      "_jt_": {
        "worker_id": "worker.1499371713.aabd4754.host.2b33d591.10.10.0.20", 
        "workflow_version": "0.6.7", 
        "jt_version": "0.1.0rc9", 
        "task_state": "completed"
      }, 
      "idx_file": null, 
      "allowed_upload": true, 
      "file_md5sum": "5c0de1fd52a2068b254173fc030cd199", 
      "file": "/home/ubuntu/jtracker/worker.1499371713.aabd4754.host.2b33d591.10.10.0.20/job.EGAR00001195594.LINC-JP.HCC117T.EGAN00001196886/task.prepare_metadata_xml/bundle.EGAR00001195594.xml", 
      "file_size": 3503, 
      "runtime": {
        "task_start": 1500243079, 
        "task_stop": 1500243084
      }
    }
  ], 
  "input": {
    "file_name": "bundle.EGAR00001195594.xml", 
    "object_id": "2173eb12-f98c-57ef-9994-4a45e71b3ac3", 
    "file_md5sum": "5c0de1fd52a2068b254173fc030cd199", 
    "file": "/home/ubuntu/jtracker/worker.1499371713.aabd4754.host.2b33d591.10.10.0.20/job.EGAR00001195594.LINC-JP.HCC117T.EGAN00001196886/task.prepare_metadata_xml/bundle.EGAR00001195594.xml", 
    "file_size": 3503, 
    "bundle_id": "EGAR00001195594", 
    "project_code": "LINC-JP"
  }, 
  "runtime": {
    "docker": null
  }
}