{
  "task": "xml_upload_to_aws", 
  "depends_on": [
    "completed@prepare_metadata_xml"
  ], 
  "tool": "upload_to_aws", 
  "command": "upload_to_aws.py", 
  "output": [
    {
      "idx_file_size": 0, 
      "idx_file_md5sum": null, 
      "_jt_": {
        "worker_id": "worker.1502296938.163e6a77.host.231181a3.10.10.1.7", 
        "workflow_version": "0.6.7", 
        "jt_version": "0.1.0rc9", 
        "task_state": "completed"
      }, 
      "idx_file": null, 
      "allowed_upload": false, 
      "file_md5sum": "379cfbf84bc08e91412fd23cb5852745", 
      "file": "/home/ubuntu/jtracker/worker.1502296938.163e6a77.host.231181a3.10.10.1.7/job.EGAR00001262253.BTCA-JP.BD190T.EGAN00001246990/task.prepare_metadata_xml/bundle.EGAR00001262253.xml", 
      "file_size": 0, 
      "runtime": {
        "task_start": 1502869774, 
        "task_stop": 1502869774
      }
    }
  ], 
  "input": {
    "file_name": "bundle.EGAR00001262253.xml", 
    "object_id": "99cef9d5-3fdf-5f5b-b23b-df1edf5a783a", 
    "file_md5sum": "379cfbf84bc08e91412fd23cb5852745", 
    "file": "/home/ubuntu/jtracker/worker.1502296938.163e6a77.host.231181a3.10.10.1.7/job.EGAR00001262253.BTCA-JP.BD190T.EGAN00001246990/task.prepare_metadata_xml/bundle.EGAR00001262253.xml", 
    "file_size": 3184, 
    "bundle_id": "EGAR00001262253", 
    "project_code": "BTCA-JP"
  }, 
  "runtime": {
    "docker": null
  }
}