{
  "task": "xml_file_upload", 
  "depends_on": [
    "completed@xml_upload_to_aws", 
    "completed@prepare_metadata_xml"
  ], 
  "tool": "upload", 
  "command": "upload.py", 
  "input": {
    "file_name": "bundle.EGAR00001118622.xml", 
    "object_id": "f4fe8db8-4ca0-573a-b1b0-e1ea670c5f32", 
    "file_md5sum": "e5c081866d9e6627cd154ddac2701c63", 
    "file": "/home/ubuntu/jtracker/worker.1499368884.8d58d2e6.host.2b33d591.10.10.0.20/job.EGAR00001118622.LINC-JP.HCC118T.EGAN00001086058/task.prepare_metadata_xml/bundle.EGAR00001118622.xml", 
    "file_size": 3669, 
    "bundle_id": "EGAR00001118622"
  }, 
  "runtime": {
    "docker": null
  }
}