{
  "task": "xml_file_upload", 
  "depends_on": [
    "completed@xml_upload_to_aws", 
    "completed@prepare_metadata_xml"
  ], 
  "tool": "upload", 
  "command": "upload.py", 
  "input": {
    "file_name": "bundle.EGAR00001110170.xml", 
    "object_id": "d80dff87-6b9f-5c80-a34a-174f452232e8", 
    "file_md5sum": "22b618a1d5ebbdee7d4b5e070cddc1d6", 
    "file": "/home/ubuntu/jtracker/worker.1499368884.8d58d2e6.host.2b33d591.10.10.0.20/job.EGAR00001110170.LINC-JP.HCC11T.EGAN00001085968/task.prepare_metadata_xml/bundle.EGAR00001110170.xml", 
    "file_size": 3667, 
    "bundle_id": "EGAR00001110170"
  }, 
  "runtime": {
    "docker": null
  }
}