{
  "task": "xml_upload_to_aws", 
  "depends_on": [
    "completed@prepare_metadata_xml"
  ], 
  "tool": "upload_to_aws", 
  "command": "upload_to_aws.py", 
  "input": {
    "file_name": "bundle.EGAR00001257134.xml", 
    "object_id": "52e8c92c-4965-50cc-8d52-e65bafcd5846", 
    "file_md5sum": "7c1d310846e69f782bbb455e0705b69c", 
    "file": "/home/ubuntu/jtracker/worker.1500669053.c36d31ad.host.032f1807.10.10.0.3/job.EGAR00001257134.BTCA-JP.BD50T.EGAN00001246854/task.prepare_metadata_xml/bundle.EGAR00001257134.xml", 
    "file_size": 3176, 
    "bundle_id": "EGAR00001257134", 
    "project_code": "BTCA-JP"
  }, 
  "runtime": {
    "docker": null
  }
}