{
  "task": "xml_file_upload", 
  "depends_on": [
    "completed@xml_upload_to_aws", 
    "completed@prepare_metadata_xml"
  ], 
  "tool": "upload", 
  "command": "upload.py", 
  "input": {
    "file_name": "bundle.EGAR00001109922.xml", 
    "object_id": "5e5b2f4b-692b-53fb-86bd-690fd8891177", 
    "file_md5sum": "f23d71d48c1210b66a1c6e7cf985a476", 
    "file": "/home/ubuntu/jtracker/worker.1499368884.8d58d2e6.host.2b33d591.10.10.0.20/job.EGAR00001109922.LINC-JP.HCC6T.EGAN00001085965/task.prepare_metadata_xml/bundle.EGAR00001109922.xml", 
    "file_size": 3655, 
    "bundle_id": "EGAR00001109922"
  }, 
  "runtime": {
    "docker": null
  }
}