{
  "task": "xml_upload_to_aws", 
  "depends_on": [
    "completed@prepare_metadata_xml"
  ], 
  "tool": "upload_to_aws", 
  "command": "upload_to_aws.py", 
  "input": {
    "file_name": "bundle.EGAR00001256870.xml", 
    "object_id": "0e629208-676e-556b-918d-81f33d0131a1", 
    "file_md5sum": "7cb527a9421f39cd24685d7782c67eda", 
    "file": "/home/ubuntu/jtracker/worker.1499371713.aabd4754.host.2b33d591.10.10.0.20/job.EGAR00001256870.BTCA-JP.BD45T.EGAN00001246849/task.prepare_metadata_xml/bundle.EGAR00001256870.xml", 
    "file_size": 3176, 
    "bundle_id": "EGAR00001256870", 
    "project_code": "BTCA-JP"
  }, 
  "runtime": {
    "docker": null
  }
}