{
  "task": "xml_file_upload", 
  "depends_on": [
    "completed@xml_upload_to_aws", 
    "completed@prepare_metadata_xml"
  ], 
  "tool": "upload", 
  "command": "upload.py", 
  "input": {
    "file_name": "bundle.EGAR00001264640.xml", 
    "object_id": "c97e3863-b185-5e3c-b789-66e58a59c8d1", 
    "file_md5sum": "a9659dacac69e94dc8b92c598d74deaf", 
    "file": "/home/ubuntu/jtracker/worker.1499371713.aabd4754.host.2b33d591.10.10.0.20/job.EGAR00001264640.BTCA-JP.BD243T.EGAN00001247036/task.prepare_metadata_xml/bundle.EGAR00001264640.xml", 
    "file_size": 3186, 
    "bundle_id": "EGAR00001264640"
  }, 
  "runtime": {
    "docker": null
  }
}