{
  "task": "xml_file_upload", 
  "depends_on": [
    "completed@xml_upload_to_aws", 
    "completed@prepare_metadata_xml"
  ], 
  "tool": "upload", 
  "command": "upload.py", 
  "input": {
    "file_name": "bundle.EGAR00001195306.xml", 
    "object_id": "d09a7dd3-9ffc-5c22-831d-b3f9f5d0631e", 
    "file_md5sum": "d65ee1be38f23068dcb27a1b4581b97f", 
    "file": "/home/ubuntu/jtracker/worker.1499371713.aabd4754.host.2b33d591.10.10.0.20/job.EGAR00001195306.LINC-JP.HCC103T.EGAN00001196884/task.prepare_metadata_xml/bundle.EGAR00001195306.xml", 
    "file_size": 3505, 
    "bundle_id": "EGAR00001195306"
  }, 
  "runtime": {
    "docker": null
  }
}