{
  "task": "xml_file_upload", 
  "depends_on": [
    "completed@xml_upload_to_aws", 
    "completed@prepare_metadata_xml"
  ], 
  "tool": "upload", 
  "command": "upload.py", 
  "output": [
    {
      "_jt_": {
        "worker_id": "worker.1500669053.c36d31ad.host.032f1807.10.10.0.3", 
        "workflow_version": "0.6.7", 
        "jt_version": "0.1.0rc9", 
        "task_state": "completed"
      }, 
      "runtime": {
        "task_start": 1500759203, 
        "task_stop": 1500759218
      }
    }
  ], 
  "input": {
    "file_name": "bundle.EGAR00001263483.xml", 
    "object_id": "27f19a2c-8d9f-5436-8f96-cb7ca319f956", 
    "file_md5sum": "0013d31a369ff28100506c01f762532d", 
    "file": "/home/ubuntu/jtracker/worker.1500669053.c36d31ad.host.032f1807.10.10.0.3/job.EGAR00001263483.BTCA-JP.BD215T.EGAN00001247008/task.prepare_metadata_xml/bundle.EGAR00001263483.xml", 
    "file_size": 3184, 
    "bundle_id": "EGAR00001263483"
  }, 
  "runtime": {
    "docker": null
  }
}