{
  "task": "xml_upload_to_aws", 
  "depends_on": [
    "completed@prepare_metadata_xml"
  ], 
  "tool": "upload_to_aws", 
  "command": "upload_to_aws.py", 
  "output": [
    {
      "idx_file_size": 0, 
      "idx_file_md5sum": null, 
      "_jt_": {
        "worker_id": "worker.1499371713.aabd4754.host.2b33d591.10.10.0.20", 
        "workflow_version": "0.6.7", 
        "jt_version": "0.1.0rc9", 
        "task_state": "completed"
      }, 
      "idx_file": null, 
      "allowed_upload": true, 
      "file_md5sum": "3046503352e6dd60d22745545ebe3271", 
      "file": "/home/ubuntu/jtracker/worker.1499371713.aabd4754.host.2b33d591.10.10.0.20/job.EGAR00001199540.LINC-JP.HCC59T.EGAN00001196877/task.prepare_metadata_xml/bundle.EGAR00001199540.xml", 
      "file_size": 3503, 
      "runtime": {
        "task_start": 1500178043, 
        "task_stop": 1500178049
      }
    }
  ], 
  "input": {
    "file_name": "bundle.EGAR00001199540.xml", 
    "object_id": "7479cdf5-5d74-5116-938e-315ad35fefc0", 
    "file_md5sum": "3046503352e6dd60d22745545ebe3271", 
    "file": "/home/ubuntu/jtracker/worker.1499371713.aabd4754.host.2b33d591.10.10.0.20/job.EGAR00001199540.LINC-JP.HCC59T.EGAN00001196877/task.prepare_metadata_xml/bundle.EGAR00001199540.xml", 
    "file_size": 3503, 
    "bundle_id": "EGAR00001199540", 
    "project_code": "LINC-JP"
  }, 
  "runtime": {
    "docker": null
  }
}