{
  "task": "xml_file_upload", 
  "depends_on": [
    "completed@xml_upload_to_aws", 
    "completed@prepare_metadata_xml"
  ], 
  "tool": "upload", 
  "command": "upload.py", 
  "output": [
    {
      "_jt_": {
        "worker_id": "worker.1500669053.c36d31ad.host.032f1807.10.10.0.3", 
        "workflow_version": "0.6.7", 
        "jt_version": "0.1.0rc9", 
        "task_state": "completed"
      }, 
      "runtime": {
        "task_start": 1500749193, 
        "task_stop": 1500749208
      }
    }
  ], 
  "input": {
    "file_name": "bundle.EGAR00001261884.xml", 
    "object_id": "94c96560-8765-5d4b-9b98-03aaff5d2ce3", 
    "file_md5sum": "da49432a970e02629c9d3048aacdf3b8", 
    "file": "/home/ubuntu/jtracker/worker.1500669053.c36d31ad.host.032f1807.10.10.0.3/job.EGAR00001261884.BTCA-JP.BD180T.EGAN00001246980/task.prepare_metadata_xml/bundle.EGAR00001261884.xml", 
    "file_size": 3186, 
    "bundle_id": "EGAR00001261884"
  }, 
  "runtime": {
    "docker": null
  }
}