{
  "task": "xml_file_upload", 
  "depends_on": [
    "completed@xml_upload_to_aws", 
    "completed@prepare_metadata_xml"
  ], 
  "tool": "upload", 
  "command": "upload.py", 
  "output": [
    {
      "_jt_": {
        "worker_id": "worker.1502296938.163e6a77.host.231181a3.10.10.1.7", 
        "workflow_version": "0.6.7", 
        "jt_version": "0.1.0rc9", 
        "task_state": "completed"
      }, 
      "runtime": {
        "task_start": 1502542066, 
        "task_stop": 1502542084
      }
    }
  ], 
  "input": {
    "file_name": "bundle.EGAR00001257641.xml", 
    "object_id": "6c425468-7abb-55b9-82aa-b96f0ffe95d8", 
    "file_md5sum": "5a1676bf35c63aedcd000c44b912cc93", 
    "file": "/home/ubuntu/jtracker/worker.1502296938.163e6a77.host.231181a3.10.10.1.7/job.EGAR00001257641.BTCA-JP.BD64T.EGAN00001246868/task.prepare_metadata_xml/bundle.EGAR00001257641.xml", 
    "file_size": 3174, 
    "bundle_id": "EGAR00001257641"
  }, 
  "runtime": {
    "docker": null
  }
}