{
  "task": "xml_file_upload", 
  "depends_on": [
    "completed@xml_upload_to_aws", 
    "completed@prepare_metadata_xml"
  ], 
  "tool": "upload", 
  "command": "upload.py", 
  "output": [
    {
      "_jt_": {
        "worker_id": "worker.1503519202.ce7b02df.host.4b92f40d.10.10.0.7", 
        "workflow_version": "0.6.11", 
        "jt_version": "0.1.0rc9", 
        "task_state": "completed"
      }, 
      "runtime": {
        "task_start": 1503545812, 
        "task_stop": 1503545830
      }
    }
  ], 
  "input": {
    "file_name": "bundle.EGAR00001526561.xml", 
    "object_id": "1ad0c8d4-2ca3-52f8-944f-0ce589c24a43", 
    "file_md5sum": "8cae58490ef9eed312d67c146212f1de", 
    "file": "/home/ubuntu/jtracker/worker.1503519202.ce7b02df.host.4b92f40d.10.10.0.7/job.EGAR00001526561.UTCA-FR.DA1600F.EGAN00001487467/task.prepare_metadata_xml/bundle.EGAR00001526561.xml", 
    "file_size": 4024, 
    "bundle_id": "EGAR00001526561"
  }, 
  "runtime": {
    "docker": null
  }
}