{
  "task": "xml_file_upload", 
  "depends_on": [
    "completed@xml_upload_to_aws", 
    "completed@prepare_metadata_xml"
  ], 
  "tool": "upload", 
  "command": "upload.py", 
  "output": [
    {
      "_jt_": {
        "worker_id": "worker.1502296938.163e6a77.host.231181a3.10.10.1.7", 
        "workflow_version": "0.6.7", 
        "jt_version": "0.1.0rc9", 
        "task_state": "completed"
      }, 
      "runtime": {
        "task_start": 1502503502, 
        "task_stop": 1502503518
      }
    }
  ], 
  "input": {
    "file_name": "bundle.EGAR00001257829.xml", 
    "object_id": "de4c40eb-335b-55fb-9320-6c7b66447357", 
    "file_md5sum": "d67748b22c53f6312147d1fbeea7ffab", 
    "file": "/home/ubuntu/jtracker/worker.1502296938.163e6a77.host.231181a3.10.10.1.7/job.EGAR00001257829.BTCA-JP.BD69T.EGAN00001246873/task.prepare_metadata_xml/bundle.EGAR00001257829.xml", 
    "file_size": 3176, 
    "bundle_id": "EGAR00001257829"
  }, 
  "runtime": {
    "docker": null
  }
}