{
  "task": "xml_upload_to_aws", 
  "depends_on": [
    "completed@prepare_metadata_xml"
  ], 
  "tool": "upload_to_aws", 
  "command": "upload_to_aws.py", 
  "input": {
    "file_name": "bundle.EGAR00001262132.xml", 
    "object_id": "5ecde22e-fe30-587a-8580-c65d0406eb22", 
    "file_md5sum": "fb6357c64d4327692f9837ac6d2ac7a5", 
    "file": "/home/ubuntu/jtracker/worker.1502296920.7ba09f8b.host.231181a3.10.10.1.7/job.EGAR00001262132.BTCA-JP.BD186T.EGAN00001246986/task.prepare_metadata_xml/bundle.EGAR00001262132.xml", 
    "file_size": 3186, 
    "bundle_id": "EGAR00001262132", 
    "project_code": "BTCA-JP"
  }, 
  "runtime": {
    "docker": null
  }
}