{
  "task": "xml_file_upload", 
  "depends_on": [
    "completed@xml_upload_to_aws", 
    "completed@prepare_metadata_xml"
  ], 
  "tool": "upload", 
  "command": "upload.py", 
  "output": [
    {
      "_jt_": {
        "worker_id": "worker.1499371713.aabd4754.host.2b33d591.10.10.0.20", 
        "workflow_version": "0.6.7", 
        "jt_version": "0.1.0rc9", 
        "task_state": "completed"
      }, 
      "runtime": {
        "task_start": 1501308109, 
        "task_stop": 1501308125
      }
    }
  ], 
  "input": {
    "file_name": "bundle.EGAR00001257965.xml", 
    "object_id": "bd86ed36-4f6f-5fe3-b4c7-14ea470cbd0a", 
    "file_md5sum": "84ee0eb4126873133408690c37324b67", 
    "file": "/home/ubuntu/jtracker/worker.1499371713.aabd4754.host.2b33d591.10.10.0.20/job.EGAR00001257965.BTCA-JP.BD72T.EGAN00001246876/task.prepare_metadata_xml/bundle.EGAR00001257965.xml", 
    "file_size": 3174, 
    "bundle_id": "EGAR00001257965"
  }, 
  "runtime": {
    "docker": null
  }
}