{
  "task": "decryption", 
  "depends_on": [
    "completed@download.EGAF00000534789"
  ], 
  "tool": "decryption", 
  "command": "decryption.py", 
  "input": {
    "file_name": "{{file_name@download.EGAF00000534789}}", 
    "file_md5sum": "{{file_md5sum@download.EGAF00000534789}}", 
    "ega_file_id": "{{ega_file_id@download.EGAF00000534789}}", 
    "object_id": "{{object_id@download.EGAF00000534789}}", 
    "input_file": "{{file@download.EGAF00000534789}}"
  }, 
  "runtime": {
    "docker": null
  }
}