{
  "task": "xml_file_upload", 
  "depends_on": [
    "completed@xml_upload_to_aws", 
    "completed@prepare_metadata_xml"
  ], 
  "tool": "upload", 
  "command": "upload.py", 
  "output": [
    {
      "_jt_": {
        "worker_id": "worker.1499371713.aabd4754.host.2b33d591.10.10.0.20", 
        "workflow_version": "0.6.7", 
        "jt_version": "0.1.0rc9", 
        "task_state": "completed"
      }, 
      "runtime": {
        "task_start": 1500011773, 
        "task_stop": 1500011788
      }
    }
  ], 
  "input": {
    "file_name": "bundle.EGAR00001196016.xml", 
    "object_id": "dad2977a-534a-52f3-adf3-0484faf90c33", 
    "file_md5sum": "f0e78723c89834ff90de8378fb222295", 
    "file": "/home/ubuntu/jtracker/worker.1499371713.aabd4754.host.2b33d591.10.10.0.20/job.EGAR00001196016.LINC-JP.HCC126T.EGAN00001196888/task.prepare_metadata_xml/bundle.EGAR00001196016.xml", 
    "file_size": 3505, 
    "bundle_id": "EGAR00001196016"
  }, 
  "runtime": {
    "docker": null
  }
}