{
  "task": "xml_file_upload", 
  "depends_on": [
    "completed@xml_upload_to_aws", 
    "completed@prepare_metadata_xml"
  ], 
  "tool": "upload", 
  "command": "upload.py", 
  "output": [
    {
      "_jt_": {
        "worker_id": "worker.1501684132.99ad8564.host.2b33d591.10.10.0.20", 
        "workflow_version": "0.6.7", 
        "jt_version": "0.1.0rc9", 
        "task_state": "completed"
      }, 
      "runtime": {
        "task_start": 1501817250, 
        "task_stop": 1501817266
      }
    }
  ], 
  "input": {
    "file_name": "bundle.EGAR00001258763.xml", 
    "object_id": "61c94263-85c0-55c2-bbdb-b29de20d705e", 
    "file_md5sum": "5271f5a44c9c2c38499fb75eca77552d", 
    "file": "/home/ubuntu/jtracker/worker.1501684132.99ad8564.host.2b33d591.10.10.0.20/job.EGAR00001258763.BTCA-JP.BD95T.EGAN00001246898/task.prepare_metadata_xml/bundle.EGAR00001258763.xml", 
    "file_size": 3176, 
    "bundle_id": "EGAR00001258763"
  }, 
  "runtime": {
    "docker": null
  }
}