{
  "task": "xml_upload_to_aws", 
  "depends_on": [
    "completed@prepare_metadata_xml"
  ], 
  "tool": "upload_to_aws", 
  "command": "upload_to_aws.py", 
  "input": {
    "file_name": "bundle.EGAR00001258793.xml", 
    "object_id": "239f4c4c-d1dd-57c9-8c7e-3c6caaf2f3a3", 
    "file_md5sum": "efbcc3bf9e6a44c621ea83e51992af39", 
    "file": "/home/ubuntu/jtracker/worker.1501684132.99ad8564.host.2b33d591.10.10.0.20/job.EGAR00001258793.BTCA-JP.BD96T.EGAN00001246899/task.prepare_metadata_xml/bundle.EGAR00001258793.xml", 
    "file_size": 3176, 
    "bundle_id": "EGAR00001258793", 
    "project_code": "BTCA-JP"
  }, 
  "runtime": {
    "docker": null
  }
}