{
  "task": "xml_file_upload", 
  "depends_on": [
    "completed@xml_upload_to_aws", 
    "completed@prepare_metadata_xml"
  ], 
  "tool": "upload", 
  "command": "upload.py", 
  "output": [
    {
      "_jt_": {
        "worker_id": "worker.1499368884.8d58d2e6.host.2b33d591.10.10.0.20", 
        "workflow_version": "0.6.7", 
        "jt_version": "0.1.0rc9", 
        "task_state": "completed"
      }, 
      "runtime": {
        "task_start": 1500054508, 
        "task_stop": 1500054523
      }
    }
  ], 
  "input": {
    "file_name": "bundle.EGAR00001118802.xml", 
    "object_id": "a70ed278-42dd-5c1e-ada9-2413fd28e89c", 
    "file_md5sum": "10d888cad53cf09709fa5daaf1b7c0c3", 
    "file": "/home/ubuntu/jtracker/worker.1499368884.8d58d2e6.host.2b33d591.10.10.0.20/job.EGAR00001118802.LINC-JP.HCC119T.EGAN00001086059/task.prepare_metadata_xml/bundle.EGAR00001118802.xml", 
    "file_size": 3669, 
    "bundle_id": "EGAR00001118802"
  }, 
  "runtime": {
    "docker": null
  }
}