{
  "task": "xml_upload_to_aws", 
  "depends_on": [
    "completed@prepare_metadata_xml"
  ], 
  "tool": "upload_to_aws", 
  "command": "upload_to_aws.py", 
  "input": {
    "file_name": "bundle.EGAR00001118721.xml", 
    "object_id": "c4d61826-7f35-5a48-beb6-6bc66c824eeb", 
    "file_md5sum": "c861d32ce04f1e0911190a2cc005856d", 
    "file": "/home/ubuntu/jtracker/worker.1499371713.aabd4754.host.2b33d591.10.10.0.20/job.EGAR00001118721.LINC-JP.HCC119T.EGAN00001086059/task.prepare_metadata_xml/bundle.EGAR00001118721.xml", 
    "file_size": 3665, 
    "bundle_id": "EGAR00001118721", 
    "project_code": "LINC-JP"
  }, 
  "runtime": {
    "docker": null
  }
}