{
  "task": "xml_upload_to_aws", 
  "depends_on": [
    "completed@prepare_metadata_xml"
  ], 
  "tool": "upload_to_aws", 
  "command": "upload_to_aws.py", 
  "input": {
    "file_name": "bundle.EGAR00001195468.xml", 
    "object_id": "dd6462a9-cbda-57f4-920e-d22bc2290f79", 
    "file_md5sum": "57c77ff5ef18560e2c419d8c3af38935", 
    "file": "/home/ubuntu/jtracker/worker.1499371713.aabd4754.host.2b33d591.10.10.0.20/job.EGAR00001195468.LINC-JP.HCC112T.EGAN00001196885/task.prepare_metadata_xml/bundle.EGAR00001195468.xml", 
    "file_size": 3507, 
    "bundle_id": "EGAR00001195468", 
    "project_code": "LINC-JP"
  }, 
  "runtime": {
    "docker": null
  }
}