{
  "task": "xml_upload_to_aws", 
  "depends_on": [
    "completed@prepare_metadata_xml"
  ], 
  "tool": "upload_to_aws", 
  "command": "upload_to_aws.py", 
  "input": {
    "file_name": "bundle.EGAR00001195540.xml", 
    "object_id": "0885482b-ab7b-514a-9ea4-8af253e9341a", 
    "file_md5sum": "835550e7352ff237d81bd656ea257fd1", 
    "file": "/home/ubuntu/jtracker/worker.1499368884.8d58d2e6.host.2b33d591.10.10.0.20/job.EGAR00001195540.LINC-JP.HCC112T.EGAN00001196885/task.prepare_metadata_xml/bundle.EGAR00001195540.xml", 
    "file_size": 3511, 
    "bundle_id": "EGAR00001195540", 
    "project_code": "LINC-JP"
  }, 
  "runtime": {
    "docker": null
  }
}