{
  "task": "xml_upload_to_aws", 
  "depends_on": [
    "completed@prepare_metadata_xml"
  ], 
  "tool": "upload_to_aws", 
  "command": "upload_to_aws.py", 
  "input": {
    "file_name": "bundle.EGAR00001258370.xml", 
    "object_id": "0096786d-0e2d-55d2-8158-97c2f0c3a5ec", 
    "file_md5sum": "7fe84c8eca6ccde31bc51038983facbe", 
    "file": "/home/ubuntu/jtracker/worker.1501684062.9473501c.host.76674056.10.10.0.19/job.EGAR00001258370.BTCA-JP.BD84T.EGAN00001246888/task.prepare_metadata_xml/bundle.EGAR00001258370.xml", 
    "file_size": 3174, 
    "bundle_id": "EGAR00001258370", 
    "project_code": "BTCA-JP"
  }, 
  "runtime": {
    "docker": null
  }
}