{
  "task": "xml_file_upload", 
  "depends_on": [
    "completed@xml_upload_to_aws", 
    "completed@prepare_metadata_xml"
  ], 
  "tool": "upload", 
  "command": "upload.py", 
  "input": {
    "file_name": "bundle.EGAR00001118151.xml", 
    "object_id": "3e5286df-0540-5ad2-b1aa-0c756ed5b7ba", 
    "file_md5sum": "1dfc1c613e1dcca7f925392f93d12b61", 
    "file": "/home/ubuntu/jtracker/worker.1499368884.8d58d2e6.host.2b33d591.10.10.0.20/job.EGAR00001118151.LINC-JP.HCC111T.EGAN00001086054/task.prepare_metadata_xml/bundle.EGAR00001118151.xml", 
    "file_size": 3671, 
    "bundle_id": "EGAR00001118151"
  }, 
  "runtime": {
    "docker": null
  }
}